jag_panzer/__init__.py
jag_panzer/base_room.py
jag_panzer/dir_list.py
jag_panzer/jag_logging.py
jag_panzer/jag_util.py
jag_panzer/jagtag.py
jag_panzer/response_codes.py
jag_panzer/server.py
jag_panzer/cgi/__init__.py
jag_panzer/cgi/burn_power.py
jag_panzer/cgi/hitman.py
jag_panzer/cgi/jag.py
jag_panzer-0.2.49.dist-info/LICENSE
jag_panzer-0.2.49.dist-info/METADATA
jag_panzer-0.2.49.dist-info/WHEEL
jag_panzer-0.2.49.dist-info/top_level.txt
jag_panzer-0.2.49.dist-info/RECORD
