Metadata-Version: 2.1
Name: jag-panzer
Version: 0.2.49
Summary: Simple HTTP server allowing pure python workflow
Home-page: https://github.com/MrKleiner/jag
Author: Mr.Kleiner
Author-email: megaadrenaline1055@gmail.com
Project-URL: Bug Tracker, https://github.com/MrKleiner/jag/issues
Classifier: Programming Language :: Python :: 3
Classifier: License :: OSI Approved :: MIT License
Classifier: Operating System :: OS Independent
Requires-Python: >=3.7
License-File: LICENSE
